package com.baidu.mapapi.search;

final class b extends Thread
{
  b(String paramString, a.a parama, int paramInt1, int paramInt2)
  {
  }

  // ERROR //
  public void run()
  {
    // Byte code:
    //   0: aconst_null
    //   1: astore_1
    //   2: getstatic 34	com/baidu/mapapi/search/a:b	Ljava/util/HashMap;
    //   5: astore_2
    //   6: aload_2
    //   7: monitorenter
    //   8: getstatic 34	com/baidu/mapapi/search/a:b	Ljava/util/HashMap;
    //   11: aload_0
    //   12: getfield 15	com/baidu/mapapi/search/b:a	Ljava/lang/String;
    //   15: invokevirtual 40	java/util/HashMap:get	(Ljava/lang/Object;)Ljava/lang/Object;
    //   18: checkcast 42	java/lang/ref/SoftReference
    //   21: astore 4
    //   23: aload 4
    //   25: ifnull +44 -> 69
    //   28: aload 4
    //   30: invokevirtual 45	java/lang/ref/SoftReference:get	()Ljava/lang/Object;
    //   33: checkcast 47	com/baidu/mapapi/search/j
    //   36: astore 5
    //   38: aload 5
    //   40: ifnull +29 -> 69
    //   43: aload_0
    //   44: getfield 17	com/baidu/mapapi/search/b:b	Lcom/baidu/mapapi/search/a$a;
    //   47: aload_0
    //   48: getfield 19	com/baidu/mapapi/search/b:c	I
    //   51: aload_0
    //   52: getfield 21	com/baidu/mapapi/search/b:d	I
    //   55: aload_0
    //   56: getfield 15	com/baidu/mapapi/search/b:a	Ljava/lang/String;
    //   59: aload 5
    //   61: invokeinterface 53 5 0
    //   66: aload_2
    //   67: monitorexit
    //   68: return
    //   69: new 55	java/io/ByteArrayOutputStream
    //   72: dup
    //   73: invokespecial 56	java/io/ByteArrayOutputStream:<init>	()V
    //   76: astore 6
    //   78: aload_0
    //   79: getfield 15	com/baidu/mapapi/search/b:a	Ljava/lang/String;
    //   82: invokestatic 59	com/baidu/mapapi/search/a:a	(Ljava/lang/String;)Ljava/net/HttpURLConnection;
    //   85: astore 12
    //   87: aload 12
    //   89: astore 8
    //   91: aload 8
    //   93: ifnull +175 -> 268
    //   96: aload 8
    //   98: sipush 20000
    //   101: invokevirtual 65	java/net/HttpURLConnection:setConnectTimeout	(I)V
    //   104: aload 8
    //   106: invokevirtual 68	java/net/HttpURLConnection:connect	()V
    //   109: aload 8
    //   111: invokevirtual 72	java/net/HttpURLConnection:getResponseCode	()I
    //   114: istore 15
    //   116: aconst_null
    //   117: astore_1
    //   118: iload 15
    //   120: sipush 200
    //   123: if_icmpne +119 -> 242
    //   126: aload 8
    //   128: invokevirtual 76	java/net/HttpURLConnection:getInputStream	()Ljava/io/InputStream;
    //   131: astore_1
    //   132: sipush 2048
    //   135: newarray byte
    //   137: astore 16
    //   139: aload_1
    //   140: aload 16
    //   142: invokevirtual 82	java/io/InputStream:read	([B)I
    //   145: istore 17
    //   147: iload 17
    //   149: iconst_m1
    //   150: if_icmpeq +24 -> 174
    //   153: aload 6
    //   155: aload 16
    //   157: iconst_0
    //   158: iload 17
    //   160: invokevirtual 86	java/io/ByteArrayOutputStream:write	([BII)V
    //   163: aload_1
    //   164: aload 16
    //   166: invokevirtual 82	java/io/InputStream:read	([B)I
    //   169: istore 17
    //   171: goto -24 -> 147
    //   174: aload_0
    //   175: getfield 17	com/baidu/mapapi/search/b:b	Lcom/baidu/mapapi/search/a$a;
    //   178: ifnull +64 -> 242
    //   181: new 47	com/baidu/mapapi/search/j
    //   184: dup
    //   185: aload 6
    //   187: invokevirtual 90	java/io/ByteArrayOutputStream:toByteArray	()[B
    //   190: invokespecial 93	com/baidu/mapapi/search/j:<init>	([B)V
    //   193: astore 18
    //   195: new 42	java/lang/ref/SoftReference
    //   198: dup
    //   199: aload 18
    //   201: invokespecial 96	java/lang/ref/SoftReference:<init>	(Ljava/lang/Object;)V
    //   204: astore 19
    //   206: getstatic 34	com/baidu/mapapi/search/a:b	Ljava/util/HashMap;
    //   209: aload_0
    //   210: getfield 15	com/baidu/mapapi/search/b:a	Ljava/lang/String;
    //   213: aload 19
    //   215: invokevirtual 100	java/util/HashMap:put	(Ljava/lang/Object;Ljava/lang/Object;)Ljava/lang/Object;
    //   218: pop
    //   219: aload_0
    //   220: getfield 17	com/baidu/mapapi/search/b:b	Lcom/baidu/mapapi/search/a$a;
    //   223: aload_0
    //   224: getfield 19	com/baidu/mapapi/search/b:c	I
    //   227: aload_0
    //   228: getfield 21	com/baidu/mapapi/search/b:d	I
    //   231: aload_0
    //   232: getfield 15	com/baidu/mapapi/search/b:a	Ljava/lang/String;
    //   235: aload 18
    //   237: invokeinterface 53 5 0
    //   242: aload_1
    //   243: ifnull +7 -> 250
    //   246: aload_1
    //   247: invokevirtual 103	java/io/InputStream:close	()V
    //   250: aload 8
    //   252: ifnull +8 -> 260
    //   255: aload 8
    //   257: invokevirtual 106	java/net/HttpURLConnection:disconnect	()V
    //   260: aload_2
    //   261: monitorexit
    //   262: return
    //   263: astore_3
    //   264: aload_2
    //   265: monitorexit
    //   266: aload_3
    //   267: athrow
    //   268: aload_0
    //   269: getfield 17	com/baidu/mapapi/search/b:b	Lcom/baidu/mapapi/search/a$a;
    //   272: astore 13
    //   274: aconst_null
    //   275: astore_1
    //   276: aload 13
    //   278: ifnull -36 -> 242
    //   281: aload_0
    //   282: getfield 17	com/baidu/mapapi/search/b:b	Lcom/baidu/mapapi/search/a$a;
    //   285: aload_0
    //   286: getfield 19	com/baidu/mapapi/search/b:c	I
    //   289: aload_0
    //   290: getfield 21	com/baidu/mapapi/search/b:d	I
    //   293: aload_0
    //   294: getfield 15	com/baidu/mapapi/search/b:a	Ljava/lang/String;
    //   297: ldc 108
    //   299: invokeinterface 111 5 0
    //   304: aconst_null
    //   305: astore_1
    //   306: goto -64 -> 242
    //   309: astore 7
    //   311: aload_0
    //   312: getfield 17	com/baidu/mapapi/search/b:b	Lcom/baidu/mapapi/search/a$a;
    //   315: ifnull +26 -> 341
    //   318: aload_0
    //   319: getfield 17	com/baidu/mapapi/search/b:b	Lcom/baidu/mapapi/search/a$a;
    //   322: aload_0
    //   323: getfield 19	com/baidu/mapapi/search/b:c	I
    //   326: aload_0
    //   327: getfield 21	com/baidu/mapapi/search/b:d	I
    //   330: aload_0
    //   331: getfield 15	com/baidu/mapapi/search/b:a	Ljava/lang/String;
    //   334: ldc 108
    //   336: invokeinterface 111 5 0
    //   341: aload 7
    //   343: invokevirtual 114	java/lang/Exception:printStackTrace	()V
    //   346: aload_1
    //   347: ifnull +7 -> 354
    //   350: aload_1
    //   351: invokevirtual 103	java/io/InputStream:close	()V
    //   354: aload 8
    //   356: ifnull -96 -> 260
    //   359: aload 8
    //   361: invokevirtual 106	java/net/HttpURLConnection:disconnect	()V
    //   364: goto -104 -> 260
    //   367: astore 14
    //   369: aload 14
    //   371: invokevirtual 115	java/io/IOException:printStackTrace	()V
    //   374: goto -124 -> 250
    //   377: astore 11
    //   379: aload 11
    //   381: invokevirtual 115	java/io/IOException:printStackTrace	()V
    //   384: goto -30 -> 354
    //   387: astore 9
    //   389: aconst_null
    //   390: astore 8
    //   392: aload_1
    //   393: ifnull +7 -> 400
    //   396: aload_1
    //   397: invokevirtual 103	java/io/InputStream:close	()V
    //   400: aload 8
    //   402: ifnull +8 -> 410
    //   405: aload 8
    //   407: invokevirtual 106	java/net/HttpURLConnection:disconnect	()V
    //   410: aload 9
    //   412: athrow
    //   413: astore 10
    //   415: aload 10
    //   417: invokevirtual 115	java/io/IOException:printStackTrace	()V
    //   420: goto -20 -> 400
    //   423: astore 9
    //   425: goto -33 -> 392
    //   428: astore 7
    //   430: aconst_null
    //   431: astore 8
    //   433: aconst_null
    //   434: astore_1
    //   435: goto -124 -> 311
    //
    // Exception table:
    //   from	to	target	type
    //   8	23	263	finally
    //   28	38	263	finally
    //   43	68	263	finally
    //   69	78	263	finally
    //   246	250	263	finally
    //   255	260	263	finally
    //   260	262	263	finally
    //   264	266	263	finally
    //   350	354	263	finally
    //   359	364	263	finally
    //   369	374	263	finally
    //   379	384	263	finally
    //   396	400	263	finally
    //   405	410	263	finally
    //   410	413	263	finally
    //   415	420	263	finally
    //   96	116	309	java/lang/Exception
    //   126	147	309	java/lang/Exception
    //   153	171	309	java/lang/Exception
    //   174	242	309	java/lang/Exception
    //   268	274	309	java/lang/Exception
    //   281	304	309	java/lang/Exception
    //   246	250	367	java/io/IOException
    //   350	354	377	java/io/IOException
    //   78	87	387	finally
    //   396	400	413	java/io/IOException
    //   96	116	423	finally
    //   126	147	423	finally
    //   153	171	423	finally
    //   174	242	423	finally
    //   268	274	423	finally
    //   281	304	423	finally
    //   311	341	423	finally
    //   341	346	423	finally
    //   78	87	428	java/lang/Exception
  }
}

/* Location:           D:\Documents\Downloads\dex2jar-0.0.9.15\classes_dex2jar.jar
 * Qualified Name:     com.baidu.mapapi.search.b
 * JD-Core Version:    0.6.0
 */